yellowdog_cli/__init__.py
yellowdog_cli/abort.py
yellowdog_cli/admin.py
yellowdog_cli/boost.py
yellowdog_cli/cancel.py
yellowdog_cli/cloudwizard.py
yellowdog_cli/compare.py
yellowdog_cli/create.py
yellowdog_cli/delete.py
yellowdog_cli/download.py
yellowdog_cli/finish.py
yellowdog_cli/follow.py
yellowdog_cli/format_json.py
yellowdog_cli/hold.py
yellowdog_cli/instantiate.py
yellowdog_cli/jsonnet2json.py
yellowdog_cli/list.py
yellowdog_cli/provision.py
yellowdog_cli/remove.py
yellowdog_cli/resize.py
yellowdog_cli/show.py
yellowdog_cli/shutdown.py
yellowdog_cli/start.py
yellowdog_cli/submit.py
yellowdog_cli/terminate.py
yellowdog_cli/upload.py
yellowdog_cli/version.py
yellowdog_cli/utils/__init__.py
yellowdog_cli/utils/args.py
yellowdog_cli/utils/check_imports.py
yellowdog_cli/utils/cloudwizard_aws.py
yellowdog_cli/utils/cloudwizard_aws_types.py
yellowdog_cli/utils/cloudwizard_azure.py
yellowdog_cli/utils/cloudwizard_common.py
yellowdog_cli/utils/cloudwizard_gcp.py
yellowdog_cli/utils/compact_json.py
yellowdog_cli/utils/config_types.py
yellowdog_cli/utils/csv_data.py
yellowdog_cli/utils/entity_utils.py
yellowdog_cli/utils/follow_utils.py
yellowdog_cli/utils/interactive.py
yellowdog_cli/utils/items.py
yellowdog_cli/utils/load_config.py
yellowdog_cli/utils/load_resources.py
yellowdog_cli/utils/misc_utils.py
yellowdog_cli/utils/printing.py
yellowdog_cli/utils/property_names.py
yellowdog_cli/utils/provision_utils.py
yellowdog_cli/utils/rich_console_input_fixed.py
yellowdog_cli/utils/settings.py
yellowdog_cli/utils/start_hold_common.py
yellowdog_cli/utils/submit_utils.py
yellowdog_cli/utils/type_check.py
yellowdog_cli/utils/upload_utils.py
yellowdog_cli/utils/validate_properties.py
yellowdog_cli/utils/variables.py
yellowdog_cli/utils/wrapper.py
yellowdog_cli/utils/ydid_utils.py
yellowdog_python_examples-8.1.7.dist-info/licenses/LICENSE
yellowdog_python_examples-8.1.7.dist-info/METADATA
yellowdog_python_examples-8.1.7.dist-info/WHEEL
yellowdog_python_examples-8.1.7.dist-info/entry_points.txt
yellowdog_python_examples-8.1.7.dist-info/top_level.txt
yellowdog_python_examples-8.1.7.dist-info/RECORD
