Metadata-Version: 2.4
Name: yellowdog-python-examples
Version: 8.1.7
Summary: Python CLI commands using the YellowDog Python SDK
Author-email: YellowDog Limited <support@yellowdog.co>
License-Expression: Apache-2.0
Project-URL: Homepage, https://github.com/yellowdog/python-examples
Classifier: Programming Language :: Python
Classifier: Programming Language :: Python :: 3
Classifier: Programming Language :: Python :: 3.7
Classifier: Programming Language :: Python :: 3.8
Classifier: Programming Language :: Python :: 3.9
Classifier: Programming Language :: Python :: 3.10
Classifier: Programming Language :: Python :: 3.11
Classifier: Programming Language :: Python :: 3.12
Classifier: Programming Language :: Python :: 3.13
Classifier: Operating System :: OS Independent
Classifier: Development Status :: 4 - Beta
Requires-Python: >=3.7
License-File: LICENSE
Requires-Dist: PyPAC>=0.16.4
Requires-Dist: dateparser
Requires-Dist: python-dotenv
Requires-Dist: requests
Requires-Dist: rich==13.9.4
Requires-Dist: tabulate>=0.9.0
Requires-Dist: toml
Requires-Dist: yellowdog-sdk>=11.6.0
Provides-Extra: jsonnet
Requires-Dist: jsonnet; extra == "jsonnet"
Provides-Extra: cloudwizard
Requires-Dist: boto3; extra == "cloudwizard"
Requires-Dist: google-cloud-compute; extra == "cloudwizard"
Requires-Dist: google-cloud-storage; extra == "cloudwizard"
Requires-Dist: azure-identity; extra == "cloudwizard"
Requires-Dist: azure-mgmt-resource; extra == "cloudwizard"
Requires-Dist: azure-mgmt-network; extra == "cloudwizard"
Requires-Dist: azure-mgmt-storage; extra == "cloudwizard"
Requires-Dist: azure-mgmt-subscription; extra == "cloudwizard"
Dynamic: license-file
